_animsys_refactor/__init__.pyi
_animsys_refactor/py.typed
_bl_console_utils/__init__.pyi
_bl_console_utils/py.typed
_bl_console_utils/autocomplete/__init__.pyi
_bl_console_utils/autocomplete/complete_calltip/__init__.pyi
_bl_console_utils/autocomplete/complete_import/__init__.pyi
_bl_console_utils/autocomplete/complete_namespace/__init__.pyi
_bl_console_utils/autocomplete/intellisense/__init__.pyi
_bl_i18n_utils/__init__.pyi
_bl_i18n_utils/py.typed
_bl_i18n_utils/bl_extract_messages/__init__.pyi
_bl_i18n_utils/merge_po/__init__.pyi
_bl_i18n_utils/settings/__init__.pyi
_bl_i18n_utils/utils/__init__.pyi
_bl_i18n_utils/utils_cli/__init__.pyi
_bl_i18n_utils/utils_languages_menu/__init__.pyi
_bl_i18n_utils/utils_rtl/__init__.pyi
_bl_i18n_utils/utils_spell_check/__init__.pyi
_bl_previews_utils/__init__.pyi
_bl_previews_utils/py.typed
_bl_previews_utils/bl_previews_render/__init__.pyi
_bl_rna_utils/__init__.pyi
_bl_rna_utils/py.typed
_bl_rna_utils/data_path/__init__.pyi
_bl_text_utils/__init__.pyi
_bl_text_utils/py.typed
_bl_text_utils/external_editor/__init__.pyi
_bl_ui_utils/__init__.pyi
_bl_ui_utils/py.typed
_bl_ui_utils/layout/__init__.pyi
_blendfile_header/__init__.pyi
_blendfile_header/py.typed
_bpy_internal/__init__.pyi
_bpy_internal/py.typed
_bpy_internal/addons/__init__.pyi
_bpy_internal/addons/cli/__init__.pyi
_bpy_internal/assets/__init__.pyi
_bpy_internal/assets/remote_library_listing/__init__.pyi
_bpy_internal/assets/remote_library_listing/blender_asset_library_openapi/__init__.pyi
_bpy_internal/disk_file_hash_service/__init__.pyi
_bpy_internal/disk_file_hash_service/backend_sqlite/__init__.pyi
_bpy_internal/disk_file_hash_service/hash_service/__init__.pyi
_bpy_internal/disk_file_hash_service/types/__init__.pyi
_bpy_internal/extensions/__init__.pyi
_bpy_internal/extensions/junction_module/__init__.pyi
_bpy_internal/extensions/stale_file_manager/__init__.pyi
_bpy_internal/extensions/wheel_manager/__init__.pyi
_bpy_internal/filesystem/__init__.pyi
fake_bpy_module-20260201.dist-info/METADATA
fake_bpy_module-20260201.dist-info/WHEEL
fake_bpy_module-20260201.dist-info/top_level.txt
fake_bpy_module-20260201.dist-info/RECORD
